contalpha/VERSION
contalpha/__init__.py
contalpha/py.typed
contalpha-1.0.0a0.dist-info/LICENSE
contalpha-1.0.0a0.dist-info/METADATA
contalpha-1.0.0a0.dist-info/WHEEL
contalpha-1.0.0a0.dist-info/top_level.txt
contalpha-1.0.0a0.dist-info/RECORD
